cartman/__init__.py
cartman/app.py
cartman/compat.py
cartman/exceptions.py
cartman/text.py
cartman/ticket.py
cartman/ui.py
cartman-0.3.1.data/scripts/cm
cartman-0.3.1.dist-info/LICENSE
cartman-0.3.1.dist-info/METADATA
cartman-0.3.1.dist-info/WHEEL
cartman-0.3.1.dist-info/top_level.txt
cartman-0.3.1.dist-info/RECORD
