Metadata-Version: 2.1
Name: cartman
Version: 0.3.1
Summary: trac command-line tools
Home-page: http://tamentis.com/projects/cartman/
Author: Bertrand Janin
Author-email: Bertrand Janin <bertrand@janin.com>
License: ISC License (ISCL, BSD/MIT compatible)
Project-URL: Homepage, https://tamentis.com/projects/cartman/
Project-URL: Bug Tracker, https://github.com/tamentis/cartman/issues
Classifier: Development Status :: 4 - Beta
Classifier: Environment :: Console
Classifier: Intended Audience :: End Users/Desktop
Classifier: Intended Audience :: Developers
Classifier: License :: OSI Approved :: ISC License (ISCL)
Classifier: Operating System :: MacOS :: MacOS X
Classifier: Operating System :: Microsoft :: Windows
Classifier: Operating System :: POSIX
Classifier: Programming Language :: Python :: 2.7
Classifier: Programming Language :: Python :: 3
Classifier: Framework :: Trac
Classifier: Topic :: Software Development :: Bug Tracking
Requires-Python: >2.7,>=3.3
License-File: LICENSE
Requires-Dist: requests (>=1.2.0)
